<annotation>
	<folder>allfruits</folder>
	<filename>banana (126).jpg</filename>
	<path>F:\Yolo-FastestV2-main\my_data\allfruits\banana (126).jpg</path>
	<source>
		<database>Unknown</database>
	</source>
	<size>
		<width>640</width>
		<height>480</height>
		<depth>3</depth>
	</size>
	<segmented>0</segmented>
	<object>
		<name>banana</name>
		<pose>Unspecified</pose>
		<truncated>0</truncated>
		<difficult>0</difficult>
		<bndbox>
			<xmin>68</xmin>
			<ymin>68</ymin>
			<xmax>460</xmax>
			<ymax>382</ymax>
		</bndbox>
	</object>
</annotation>
