<annotation>
	<folder>data2</folder>
	<filename>mongo (125).jpg</filename>
	<path>C:\Users\ldd\Desktop\data2\mongo (125).jpg</path>
	<source>
		<database>Unknown</database>
	</source>
	<size>
		<width>1920</width>
		<height>1080</height>
		<depth>3</depth>
	</size>
	<segmented>0</segmented>
	<object>
		<name>mongo</name>
		<pose>Unspecified</pose>
		<truncated>0</truncated>
		<difficult>0</difficult>
		<bndbox>
			<xmin>590</xmin>
			<ymin>89</ymin>
			<xmax>968</xmax>
			<ymax>650</ymax>
		</bndbox>
	</object>
	<object>
		<name>mongo</name>
		<pose>Unspecified</pose>
		<truncated>0</truncated>
		<difficult>0</difficult>
		<bndbox>
			<xmin>962</xmin>
			<ymin>168</ymin>
			<xmax>1282</xmax>
			<ymax>677</ymax>
		</bndbox>
	</object>
	<object>
		<name>mongo</name>
		<pose>Unspecified</pose>
		<truncated>0</truncated>
		<difficult>0</difficult>
		<bndbox>
			<xmin>1172</xmin>
			<ymin>42</ymin>
			<xmax>1509</xmax>
			<ymax>537</ymax>
		</bndbox>
	</object>
</annotation>
